wxyz/yaml/__init__.py
wxyz/yaml/_version.py
wxyz/yaml/base.py
wxyz/yaml/install.json
wxyz/yaml/widget_yaml.py
wxyz/yaml/js/LICENSE.txt
wxyz/yaml/js/README.md
wxyz/yaml/js/package.json
wxyz/yaml/labextension/package.json
wxyz/yaml/labextension/static/180.98ca6f6e3da961fc6fa1.js
wxyz/yaml/labextension/static/180.98ca6f6e3da961fc6fa1.js.LICENSE.txt
wxyz/yaml/labextension/static/243.1f8482a2dfee50c8e25a.js
wxyz/yaml/labextension/static/333.66710c6e3afe010cd2d3.js
wxyz/yaml/labextension/static/568.a080d18e893c6203a3a3.js
wxyz/yaml/labextension/static/remoteEntry.14af0456df489cf8f067.js
wxyz/yaml/labextension/static/style.js
wxyz_yaml-0.5.1.data/data/share/jupyter/labextensions/@deathbeds/wxyz-yaml/install.json
wxyz_yaml-0.5.1.data/data/share/jupyter/labextensions/@deathbeds/wxyz-yaml/package.json
wxyz_yaml-0.5.1.data/data/share/jupyter/labextensions/@deathbeds/wxyz-yaml/static/180.98ca6f6e3da961fc6fa1.js
wxyz_yaml-0.5.1.data/data/share/jupyter/labextensions/@deathbeds/wxyz-yaml/static/180.98ca6f6e3da961fc6fa1.js.LICENSE.txt
wxyz_yaml-0.5.1.data/data/share/jupyter/labextensions/@deathbeds/wxyz-yaml/static/243.1f8482a2dfee50c8e25a.js
wxyz_yaml-0.5.1.data/data/share/jupyter/labextensions/@deathbeds/wxyz-yaml/static/333.66710c6e3afe010cd2d3.js
wxyz_yaml-0.5.1.data/data/share/jupyter/labextensions/@deathbeds/wxyz-yaml/static/568.a080d18e893c6203a3a3.js
wxyz_yaml-0.5.1.data/data/share/jupyter/labextensions/@deathbeds/wxyz-yaml/static/remoteEntry.14af0456df489cf8f067.js
wxyz_yaml-0.5.1.data/data/share/jupyter/labextensions/@deathbeds/wxyz-yaml/static/style.js
wxyz_yaml-0.5.1.dist-info/LICENSE.txt
wxyz_yaml-0.5.1.dist-info/METADATA
wxyz_yaml-0.5.1.dist-info/WHEEL
wxyz_yaml-0.5.1.dist-info/top_level.txt
wxyz_yaml-0.5.1.dist-info/RECORD
